indico_feed_sync/__init__.py
indico_feed_sync/blueprint.py
indico_feed_sync/forms.py
indico_feed_sync/plugin.py
indico_feed_sync/tasks.py
indico_feed_sync/util.py
indico_feed_sync/templates/indico_feed_sync/details_extra.html
indico_feed_sync/templates/indico_feed_sync/display_action_button.html
indico_feed_sync/templates/indico_feed_sync/event_action_button.html
indico_plugin_feed_sync-0.1.1.dist-info/licenses/LICENSE
indico_plugin_feed_sync-0.1.1.dist-info/METADATA
indico_plugin_feed_sync-0.1.1.dist-info/WHEEL
indico_plugin_feed_sync-0.1.1.dist-info/entry_points.txt
indico_plugin_feed_sync-0.1.1.dist-info/top_level.txt
indico_plugin_feed_sync-0.1.1.dist-info/RECORD
