Metadata-Version: 2.4
Name: indico-plugin-feed-sync
Version: 0.1.1
Summary: Indico plugin for synchronizing external Indico feeds into local events
Home-page: https://github.com/Atisom/indico-plugin-feed-sync
Author: Attila Debreczeni
Author-email: Attila Debreczeni <attila.debreczeni@dkf.hu>
License-Expression: MIT
Project-URL: Homepage, https://github.com/Atisom/indico-plugin-feed-sync
Project-URL: Source, https://github.com/Atisom/indico-plugin-feed-sync
Project-URL: Tracker, https://github.com/Atisom/indico-plugin-feed-sync
Keywords: indico,plugin,sync,events
Classifier: Development Status :: 4 - Beta
Classifier: Intended Audience :: System Administrators
Classifier: Intended Audience :: Developers
Classifier: Operating System :: OS Independent
Classifier: Programming Language :: Python :: 3
Classifier: Programming Language :: Python :: 3.11
Requires-Python: >=3.11
License-File: LICENSE
Requires-Dist: indico>=3.3
Dynamic: license-file
